inpainting/__init__.py
inpainting/challenge_metrics_2023.py
inpainting-0.0.10.dist-info/LICENSE
inpainting-0.0.10.dist-info/METADATA
inpainting-0.0.10.dist-info/WHEEL
inpainting-0.0.10.dist-info/RECORD
