Metadata-Version: 2.3
Name: inpainting
Version: 0.0.10
Summary: Official package to compute metrics for the BraTS inpainting challenge.
License: AGPL-3.0
Author: Florian Kofler
Author-email: florian.kofler@tum.de
Maintainer: Florian Kofler
Maintainer-email: florian.kofler@tum.de
Requires-Python: >=3.10
Classifier: License :: OSI Approved :: GNU Affero General Public License v3
Classifier: Programming Language :: Python :: 3
Classifier: Programming Language :: Python :: 3.10
Classifier: Programming Language :: Python :: 3.11
Classifier: Programming Language :: Python :: 3.12
Classifier: Programming Language :: Python :: 3.13
Requires-Dist: nibabel (>=3.0)
Requires-Dist: numpy (>=1.25)
Requires-Dist: torch (>=2.0.1)
Requires-Dist: torchmetrics (>=1.1.2)
Project-URL: Repository, https://github.com/BrainLesion/inpainting
